radioactive/__init__.py
radioactive/__main__.py
radioactive/actions.py
radioactive/alias.py
radioactive/app.py
radioactive/args.py
radioactive/config.py
radioactive/feature_flags.py
radioactive/ffplay.py
radioactive/filter.py
radioactive/handler.py
radioactive/help.py
radioactive/last_station.py
radioactive/mpv.py
radioactive/parser.py
radioactive/paths.py
radioactive/recorder.py
radioactive/ui.py
radioactive/utilities.py
radioactive/vlc.py
radio_active-3.0.0.dist-info/LICENSE
radio_active-3.0.0.dist-info/METADATA
radio_active-3.0.0.dist-info/WHEEL
radio_active-3.0.0.dist-info/entry_points.txt
radio_active-3.0.0.dist-info/top_level.txt
radio_active-3.0.0.dist-info/RECORD
