Metadata-Version: 2.1
Name: radio-active
Version: 3.0.0
Summary: Play and record any radio stations around the globe right from the terminal
Home-page: https://github.com/deep5050/radio-active
Author: Dipankar Pal
Author-email: dipankarpal5050@gmail.com
License: MIT
Project-URL: Source, https://github.com/deep5050/radio-active/
Project-URL: Upstream, https://api.radio-browser.info/
Keywords: pyradios wrapper radios api shortwave internet-radio cli app
Platform: UNKNOWN
Classifier: License :: OSI Approved :: MIT License
Classifier: Development Status :: 5 - Production/Stable
Classifier: Environment :: Console
Classifier: Programming Language :: Python :: 3
Classifier: Operating System :: OS Independent
Classifier: Intended Audience :: End Users/Desktop
Classifier: Topic :: Multimedia :: Sound/Audio
Requires-Python: >=3.6
License-File: LICENSE
Requires-Dist: pick
Requires-Dist: psutil
Requires-Dist: pyradios (==1.0.2)
Requires-Dist: requests
Requires-Dist: requests-cache
Requires-Dist: rich
Requires-Dist: setuptools
Requires-Dist: urllib3
Requires-Dist: zenlog
Provides-Extra: dev
Requires-Dist: black ; extra == 'dev'
Requires-Dist: flake8 (>=4.0.1) ; extra == 'dev'
Requires-Dist: twine ; extra == 'dev'
